lumparser/__init__.py
lumparser/__main__.py
lumparser/__pycache__/__init__.cpython-37.pyc
lumparser/data/parsed/Example_data.parsed
lumparser/data/td/Example01.td
lumparser/data/td/Example02.td
lumparser/data/td/Example03.td
lumparser/data/td/Example04.td
lumparser/data/td/Example05.td
lumparser/parsertools/__init__.py
lumparser/parsertools/defaultvalues.py
lumparser/parsertools/ptools.py
lumparser/parsertools/signal.py
lumparser/parsertools/signalgroup.py
lumparser/parsertools/timedrivedata.py
lumparser/parsertools/timedriveparser.py
lumparser/parsertools/__pycache__/__init__.cpython-37.pyc
lumparser/parsertools/__pycache__/defaultvalues.cpython-37.pyc
lumparser/parsertools/__pycache__/ptools.cpython-37.pyc
lumparser/parsertools/__pycache__/signal.cpython-37.pyc
lumparser/parsertools/__pycache__/signalgroup.cpython-37.pyc
lumparser/parsertools/__pycache__/timedrivedata.cpython-37.pyc
lumparser/parsertools/__pycache__/timedriveparser.cpython-37.pyc
lumparser/parsertools/fitting/__init__.py
lumparser/parsertools/fitting/fittools.py
lumparser/parsertools/fitting/functions.py
lumparser/parsertools/fitting/__pycache__/__init__.cpython-37.pyc
lumparser/parsertools/fitting/__pycache__/fittools.cpython-37.pyc
lumparser/parsertools/fitting/__pycache__/functions.cpython-37.pyc
lumparser/user_interface/__init__.py
lumparser/user_interface/anawindow.py
lumparser/user_interface/folderwindow.py
lumparser/user_interface/mainwindow.py
lumparser/user_interface/parsewindow.py
lumparser/user_interface/stdredirector.py
lumparser/user_interface/__pycache__/__init__.cpython-37.pyc
lumparser/user_interface/__pycache__/anawindow.cpython-37.pyc
lumparser/user_interface/__pycache__/mainwindow.cpython-37.pyc
lumparser/user_interface/anawindow_subframes/__init__.py
lumparser/user_interface/anawindow_subframes/anatoolframe.py
lumparser/user_interface/anawindow_subframes/fitoptionsframe.py
lumparser/user_interface/anawindow_subframes/__pycache__/__init__.cpython-37.pyc
lumparser-1.0.0.dist-info/LICENSE.txt
lumparser-1.0.0.dist-info/METADATA
lumparser-1.0.0.dist-info/WHEEL
lumparser-1.0.0.dist-info/entry_points.txt
lumparser-1.0.0.dist-info/top_level.txt
lumparser-1.0.0.dist-info/RECORD
