Metadata-Version: 2.1
Name: lumparser
Version: 1.0.0
Summary: Python library for parsing and analysing Luminescence time drive data.
Author: Fenne Marjolein Dijkema
Author-email: fmdijkema@gmail.com
License: MIT license
Project-URL: repository, https://github.com/FDijkema/LumParser
Keywords: Luminescence Time drive Luciferase Gaussia Relative light units Luminometer Spectroscopy
Requires: numpy
Requires: scipy
Requires: matplotlib
Requires-Python: >=3.7
License-File: LICENSE.txt
Requires-Dist: numpy
Requires-Dist: scipy
Requires-Dist: matplotlib
